autonomy/__init__.py
autonomy/__version__.py
autonomy/constants.py
autonomy/py.typed
autonomy/analyse/__init__.py
autonomy/analyse/constants.py
autonomy/analyse/dialogues.py
autonomy/analyse/handlers.py
autonomy/analyse/service.py
autonomy/analyse/abci/__init__.py
autonomy/analyse/abci/app_spec.py
autonomy/analyse/abci/docstrings.py
autonomy/analyse/benchmark/__init__.py
autonomy/analyse/benchmark/aggregate.py
autonomy/analyse/benchmark/html.py
autonomy/analyse/logs/__init__.py
autonomy/analyse/logs/base.py
autonomy/analyse/logs/collection.py
autonomy/analyse/logs/db.py
autonomy/chain/__init__.py
autonomy/chain/base.py
autonomy/chain/config.py
autonomy/chain/constants.py
autonomy/chain/exceptions.py
autonomy/chain/metadata.py
autonomy/chain/mint.py
autonomy/chain/service.py
autonomy/chain/tx.py
autonomy/chain/utils.py
autonomy/chain/subgraph/__init__.py
autonomy/chain/subgraph/client.py
autonomy/chain/subgraph/queries.py
autonomy/cli/__init__.py
autonomy/cli/__main__.py
autonomy/cli/analyse.py
autonomy/cli/build_images.py
autonomy/cli/core.py
autonomy/cli/deploy.py
autonomy/cli/develop.py
autonomy/cli/fetch.py
autonomy/cli/hash.py
autonomy/cli/mint.py
autonomy/cli/packages.py
autonomy/cli/publish.py
autonomy/cli/push_all.py
autonomy/cli/replay.py
autonomy/cli/scaffold_fsm.py
autonomy/cli/service.py
autonomy/cli/helpers/__init__.py
autonomy/cli/helpers/analyse.py
autonomy/cli/helpers/chain.py
autonomy/cli/helpers/deployment.py
autonomy/cli/helpers/docstring.py
autonomy/cli/helpers/env.py
autonomy/cli/helpers/fsm_spec.py
autonomy/cli/helpers/image.py
autonomy/cli/helpers/ipfs_hash.py
autonomy/cli/helpers/registry.py
autonomy/cli/utils/__init__.py
autonomy/cli/utils/click_utils.py
autonomy/configurations/__init__.py
autonomy/configurations/base.py
autonomy/configurations/constants.py
autonomy/configurations/loader.py
autonomy/configurations/validation.py
autonomy/configurations/schemas/fsm_specification_schema.json
autonomy/configurations/schemas/service_schema.json
open_autonomy-0.21.6.dist-info/licenses/AUTHORS.md
open_autonomy-0.21.6.dist-info/licenses/LICENSE
open_autonomy-0.21.6.dist-info/METADATA
open_autonomy-0.21.6.dist-info/WHEEL
open_autonomy-0.21.6.dist-info/entry_points.txt
open_autonomy-0.21.6.dist-info/top_level.txt
open_autonomy-0.21.6.dist-info/RECORD
