Metadata-Version: 2.4
Name: open-autonomy
Version: 0.21.6
Summary: A framework for the creation of autonomous agent services.
Home-page: https://github.com/valory-xyz/open-autonomy.git
Author: Valory AG
License: Apache-2.0
Project-URL: Bug Reports, https://github.com/valory-xyz/open-autonomy/issues
Project-URL: Source, https://github.com/valory/open-autonomy
Keywords: autonomy open-autonomy aea open-aea autonomous-economic-agents agent-framework multi-agent-systems multi-agent cryptocurrency cryptocurrencies dezentralized dezentralized-network
Classifier: Environment :: Console
Classifier: Environment :: Web Environment
Classifier: Development Status :: 2 - Pre-Alpha
Classifier: Intended Audience :: Developers
Classifier: License :: OSI Approved :: Apache Software License
Classifier: Natural Language :: English
Classifier: Operating System :: MacOS
Classifier: Operating System :: Microsoft
Classifier: Operating System :: Unix
Classifier: Programming Language :: Python :: 3.10
Classifier: Programming Language :: Python :: 3.11
Classifier: Topic :: Communications
Classifier: Topic :: Internet
Classifier: Topic :: Scientific/Engineering
Classifier: Topic :: Software Development
Classifier: Topic :: System
Requires-Python: >=3.10
License-File: LICENSE
License-File: AUTHORS.md
Requires-Dist: Flask<3.0.0,>=2.0.2
Requires-Dist: open-aea[all]==2.0.7
Requires-Dist: watchdog>=2.1.6
Requires-Dist: pytest==7.4.4
Requires-Dist: werkzeug==2.0.3
Requires-Dist: docker==7.1.0
Requires-Dist: hexbytes
Requires-Dist: jsonschema<4.4.0,>=4.3.0
Requires-Dist: protobuf<4.25.0,>=4.21.6
Requires-Dist: gql==3.5.0
Requires-Dist: requests<2.32.5,>=2.28.1
Requires-Dist: requests-toolbelt==1.0.0
Requires-Dist: aiohttp<4.0.0,>=3.8.5
Requires-Dist: typing_extensions<=4.13.2,>=3.10.0.2
Requires-Dist: multiaddr==0.0.9
Requires-Dist: click<9,>=8.1.0
Requires-Dist: open-aea-cli-ipfs==2.0.7
Requires-Dist: texttable==1.6.7
Requires-Dist: python-dotenv<0.22.0,>=0.14.5
Requires-Dist: pytest<7.5.0,>=7.0.0
Requires-Dist: coverage<8.0.0,>=6.4.4
Provides-Extra: cli
Requires-Dist: click<9,>=8.1.0; extra == "cli"
Requires-Dist: open-aea-cli-ipfs==2.0.7; extra == "cli"
Requires-Dist: texttable==1.6.7; extra == "cli"
Requires-Dist: python-dotenv<0.22.0,>=0.14.5; extra == "cli"
Requires-Dist: pytest<7.5.0,>=7.0.0; extra == "cli"
Requires-Dist: coverage<8.0.0,>=6.4.4; extra == "cli"
Provides-Extra: all
Requires-Dist: python-dotenv<0.22.0,>=0.14.5; extra == "all"
Requires-Dist: coverage<8.0.0,>=6.4.4; extra == "all"
Requires-Dist: click<9,>=8.1.0; extra == "all"
Requires-Dist: open-aea-cli-ipfs==2.0.7; extra == "all"
Requires-Dist: pytest<7.5.0,>=7.0.0; extra == "all"
Requires-Dist: texttable==1.6.7; extra == "all"
Dynamic: author
Dynamic: classifier
Dynamic: description
Dynamic: description-content-type
Dynamic: home-page
Dynamic: keywords
Dynamic: license
Dynamic: license-file
Dynamic: project-url
Dynamic: provides-extra
Dynamic: requires-dist
Dynamic: requires-python
Dynamic: summary
